CustomizeableSocketServer/BaseClient.py
CustomizeableSocketServer/BaseServer.py
CustomizeableSocketServer/__init__.py
CustomizeableSocketServer/buffer.py
CustomizeableSocketServer/schemas.py
CustomizeableSocketServer/__main__/__init__.py
CustomizeableSocketServer/__main__/client.py
CustomizeableSocketServer/__main__/server.py
CustomizeableSocketServer-1.0.0.dist-info/LICENSE
CustomizeableSocketServer-1.0.0.dist-info/METADATA
CustomizeableSocketServer-1.0.0.dist-info/WHEEL
CustomizeableSocketServer-1.0.0.dist-info/entry_points.txt
CustomizeableSocketServer-1.0.0.dist-info/top_level.txt
CustomizeableSocketServer-1.0.0.dist-info/RECORD
