Metadata-Version: 2.1
Name: CustomizeableSocketServer
Version: 1.0.0
Summary: deploy simple rawsocket server and clients
Author-email: Michael Ray <m.ray37990@gmail.com>
License: GNU AFFERO GENERAL PUBLIC LICENSE
Project-URL: Homepage, https://github.com/MalinkyZubr/SocketServer.git
Keywords: Socket,Server,tcp
Classifier: License :: OSI Approved :: MIT License
Classifier: Programming Language :: Python
Classifier: Programming Language :: Python :: 3
Requires-Python: >=3.9
License-File: LICENSE
Requires-Dist: pydantic
Provides-Extra: dev
